<psd filename="PupUp.psd" path="~/Documents/Development/Mobile/Snag_Art_Overhaul/Pop_Up/3x2/" width="960" height="640">	<layer name="Shade" stack="0" position="-88, -12" layerwidth="1163" layerheight="655" transformpoint="center">Shade.png</layer>	<layer name="OuterPanel" stack="1" position="90, 85" layerwidth="808" layerheight="491" transformpoint="center">OuterPanel.png</layer>	<layer name="InnerPanel" stack="2" position="100, 93" layerwidth="787" layerheight="475" transformpoint="center">InnerPanel.png</layer>	<layer name="TitleBackground" stack="3" position="100, 93" layerwidth="786" layerheight="97" transformpoint="center">TitleBackground.png</layer>	<layer name="Accept" stack="4" position="525, 455" layerwidth="342" layerheight="90" transformpoint="center">Accept.png</layer>	<layer name="Decline" stack="5" position="120, 455" layerwidth="343" layerheight="90" transformpoint="center">Decline.png</layer></psd>